snowbear/__init__.py
snowbear/dataset.py
snowbear/sql.py
snowbear-0.1.3.dist-info/WHEEL
snowbear-0.1.3.dist-info/METADATA
snowbear-0.1.3.dist-info/RECORD
