Metadata-Version: 2.1
Name: snowbear
Version: 0.1.3
Summary: 
Author: Omri Fima
Author-email: omrif@diagnosticrobotics.com
Requires-Python: >=3.7.4,<4.0
Classifier: Programming Language :: Python :: 3
Classifier: Programming Language :: Python :: 3.10
Classifier: Programming Language :: Python :: 3.8
Classifier: Programming Language :: Python :: 3.9
Requires-Dist: PyPika (>=0.48.9,<0.49.0)
Requires-Dist: pandas (>=1.3.0)
Requires-Dist: pyarrow (>=5.0.0)
Requires-Dist: snowflake-connector-python (>=2.7.0)
Requires-Dist: snowflake-sqlalchemy (>=1.3.0)
